devscore/__init__.py
devscore/data/__init__.py
devscore/data/dhs.py
devscore/data/nightlights.py
devscore/data/osm.py
devscore/data/satellite.py
devscore/data/worldpop.py
devscore/scoring/__init__.py
devscore/scoring/final_score.py
devscore/scoring/food_security.py
devscore/scoring/infrastructure.py
devscore/scoring/market_access.py
devscore/scoring/mobile_money.py
devscore/scoring/poverty.py
devscore/scoring/weights.py
devscore/utils/__init__.py
devscore/utils/geospatial.py
devscore/utils/preprocessing.py
devscore-0.1.1.dist-info/licenses/LICENSE
tests/__init__.py
tests/test_basic.py
tests/test_integration.py
tests/test_weights.py
devscore-0.1.1.dist-info/METADATA
devscore-0.1.1.dist-info/WHEEL
devscore-0.1.1.dist-info/top_level.txt
devscore-0.1.1.dist-info/RECORD
