Metadata-Version: 2.4
Name: devscore
Version: 0.1.1
Summary: Automatically compute Development Score for any geographic area using open data
Home-page: https://github.com/idrissbado/devscore
Author: Idriss Olivier Bado
Author-email: idriss.bado@example.com
Project-URL: Bug Tracker, https://github.com/idrissbado/devscore/issues
Project-URL: Documentation, https://github.com/idrissbado/devscore/blob/main/README.md
Project-URL: Source Code, https://github.com/idrissbado/devscore
Keywords: development economics poverty gis geospatial satellite remote-sensing machine-learning sdg
Classifier: Development Status :: 4 - Beta
Classifier: Intended Audience :: Science/Research
Classifier: Intended Audience :: Developers
Classifier: Topic :: Scientific/Engineering :: GIS
Classifier: Topic :: Scientific/Engineering :: Information Analysis
Classifier: License :: OSI Approved :: MIT License
Classifier: Programming Language :: Python :: 3
Classifier: Programming Language :: Python :: 3.8
Classifier: Programming Language :: Python :: 3.9
Classifier: Programming Language :: Python :: 3.10
Classifier: Programming Language :: Python :: 3.11
Classifier: Programming Language :: Python :: 3.12
Classifier: Operating System :: OS Independent
Requires-Python: >=3.8
License-File: LICENSE
Requires-Dist: numpy>=1.21.0
Requires-Dist: pandas>=1.3.0
Requires-Dist: geopandas>=0.10.0
Requires-Dist: rasterio>=1.2.0
Requires-Dist: osmnx>=1.2.0
Requires-Dist: scikit-learn>=1.0.0
Requires-Dist: xgboost>=1.5.0
Requires-Dist: requests>=2.26.0
Requires-Dist: h3>=3.7.0
Requires-Dist: shapely>=1.8.0
Requires-Dist: pyproj>=3.2.0
Requires-Dist: matplotlib>=3.4.0
Requires-Dist: seaborn>=0.11.0
Provides-Extra: earthengine
Requires-Dist: earthengine-api>=0.1.300; extra == "earthengine"
Provides-Extra: dev
Requires-Dist: pytest>=7.0.0; extra == "dev"
Requires-Dist: black>=22.0.0; extra == "dev"
Requires-Dist: flake8>=4.0.0; extra == "dev"
Dynamic: author
Dynamic: author-email
Dynamic: classifier
Dynamic: description
Dynamic: description-content-type
Dynamic: home-page
Dynamic: keywords
Dynamic: license-file
Dynamic: project-url
Dynamic: provides-extra
Dynamic: requires-dist
Dynamic: requires-python
Dynamic: summary
